lebai_client/main.py
lebai_client-0.4.1.dist-info/METADATA
lebai_client-0.4.1.dist-info/WHEEL
lebai_client-0.4.1.dist-info/entry_points.txt
lebai_client-0.4.1.dist-info/RECORD
