Metadata-Version: 2.4
Name: lebai-client
Version: 0.4.1
Summary: Dora Node client for lebai robotic arms.
License: MIT
Author: dora-rs team
Requires-Python: >=3.9
Classifier: License :: OSI Approved :: MIT License
Classifier: Programming Language :: Python :: 3
Classifier: Programming Language :: Python :: 3.9
Classifier: Programming Language :: Python :: 3.10
Classifier: Programming Language :: Python :: 3.11
Classifier: Programming Language :: Python :: 3.12
Classifier: Programming Language :: Python :: 3.13
Classifier: Programming Language :: Python :: 3.14
Requires-Dist: dora-rs (>=0.3.6rc0)
Requires-Dist: lebai-sdk (>=0.2.17)
